{
    "mail": "bernadinelchavez@rhyta.com",
    "password": "v4o3NeMULO",
    "headless": false,
    "proxy_ip": "",
    "proxy_prt": "",
    "proxy_lgn": "",
    "proxy_pwd": "",
    "name": "Bernadine L. Chavez",
    "nikname": "bernadinelchavez98Kk",
    "workFakeEmail": "http://www.fakemailgenerator.com/#/rhyta.com/bernadinelchavez/",
    "folderPath": "../ph-sessions/bernadinelchavez@rhyta.com",
    "userDataDirPath": "../ph-sessions/bernadinelchavez@rhyta.com/userDataDir",
    "phRegistered": true

}
